colorizers/__init__.py
colorizers/base_color.py
colorizers/easy.py
colorizers/eccv16.py
colorizers/siggraph17.py
colorizers/util.py
rz_colorization-1.0.5.dist-info/LICENSE
rz_colorization-1.0.5.dist-info/METADATA
rz_colorization-1.0.5.dist-info/WHEEL
rz_colorization-1.0.5.dist-info/top_level.txt
rz_colorization-1.0.5.dist-info/RECORD
