Metadata-Version: 2.1
Name: rz-colorization
Version: 1.0.5
Summary: Rich Zhang's colorization model in the form of an easy to use python package.
Home-page: https://github.com/arnavg115/colorization
Author: Arnav G.
License: MIT
Platform: UNKNOWN
Classifier: License :: OSI Approved :: MIT License
Classifier: Programming Language :: Python :: 3
Classifier: Programming Language :: Python :: 3.7
Requires-Dist: torch
Requires-Dist: scikit-image
Requires-Dist: numpy
Requires-Dist: matplotlib
Requires-Dist: Pillow
